tamil_lemmatizer/__init__.py
tamil_lemmatizer/model.py
tamil_lemmatizer/tamil_lemmatizer.py
tamil_lemmatizer/tokenizer.py
tamil_lemmatizer/vocab.py
tamil_lemmatizer-0.0.2.dist-info/METADATA
tamil_lemmatizer-0.0.2.dist-info/WHEEL
tamil_lemmatizer-0.0.2.dist-info/licenses/LICENSE
tamil_lemmatizer-0.0.2.dist-info/RECORD
