Metadata-Version: 2.4
Name: tamil_lemmatizer
Version: 0.0.2
Summary: Tamil word lemmatizer. Converts inflected Tamil words into base lemma.
Project-URL: Homepage, https://github.com/Hemanthkumar2112
Project-URL: Issues, https://github.com/Hemanthkumar2112
Author-email: Hemanth thunder <hemanthmurugan21@gmail.com>
License-File: LICENSE
Classifier: Intended Audience :: Science/Research
Classifier: License :: OSI Approved :: MIT License
Classifier: Natural Language :: Tamil
Classifier: Operating System :: OS Independent
Classifier: Programming Language :: Python :: 3
Classifier: Topic :: Scientific/Engineering :: Artificial Intelligence
Classifier: Topic :: Text Processing :: Linguistic
Requires-Python: >=3.0
Requires-Dist: huggingface-hub>=1.1.2
